{
  "arms": [
    "baseline",
    "P_min",
    "P_equ",
    "P_max"
  ],
  "c_version": "C-v0.12.0+PARTIAL",
  "cells": [
    {
      "acc_task1_final": 0.094,
      "acc_task1_initial": 0.188,
      "arm": "baseline",
      "excluded_underperforming_baseline": true,
      "hp_combo_id": "C5",
      "recombine_strategy": "mog",
      "retention": 0.5,
      "run_id": "9a4f613768569500d1b77472db83eeb5",
      "seed": 0,
      "wall_time_s": 21.983036041259766
    },
    {
      "acc_task1_final": 0.064,
      "acc_task1_initial": 0.209,
      "arm": "baseline",
      "excluded_underperforming_baseline": false,
      "hp_combo_id": "C5",
      "recombine_strategy": "mog",
      "retention": 0.30622009569377995,
      "run_id": "38462f730c4688aee317cbd8cf761979",
      "seed": 1,
      "wall_time_s": 21.52749490737915
    },
    {
      "acc_task1_final": 0.107,
      "acc_task1_initial": 0.209,
      "arm": "baseline",
      "excluded_underperforming_baseline": false,
      "hp_combo_id": "C5",
      "recombine_strategy": "mog",
      "retention": 0.5119617224880383,
      "run_id": "c111d36f3f049c307dbf2030977f52c0",
      "seed": 2,
      "wall_time_s": 21.035659074783325
    },
    {
      "acc_task1_final": 0.079,
      "acc_task1_initial": 0.27,
      "arm": "baseline",
      "excluded_underperforming_baseline": false,
      "hp_combo_id": "C5",
      "recombine_strategy": "mog",
      "retention": 0.29259259259259257,
      "run_id": "60a85e5a4c65eeb6c880e164362cbb92",
      "seed": 3,
      "wall_time_s": 21.091740369796753
    },
    {
      "acc_task1_final": 0.083,
      "acc_task1_initial": 0.268,
      "arm": "baseline",
      "excluded_underperforming_baseline": false,
      "hp_combo_id": "C5",
      "recombine_strategy": "mog",
      "retention": 0.30970149253731344,
      "run_id": "36b002f14600a62f13dd280a5d16da53",
      "seed": 4,
      "wall_time_s": 20.713452100753784
    },
    {
      "acc_task1_final": 0.073,
      "acc_task1_initial": 0.238,
      "arm": "baseline",
      "excluded_underperforming_baseline": false,
      "hp_combo_id": "C5",
      "recombine_strategy": "mog",
      "retention": 0.3067226890756303,
      "run_id": "da15a75153f1035463be8dbc316042e6",
      "seed": 5,
      "wall_time_s": 21.257729053497314
    },
    {
      "acc_task1_final": 0.082,
      "acc_task1_initial": 0.247,
      "arm": "baseline",
      "excluded_underperforming_baseline": false,
      "hp_combo_id": "C5",
      "recombine_strategy": "mog",
      "retention": 0.3319838056680162,
      "run_id": "fee6aebf59f7d22198fc44bc5cdd72d0",
      "seed": 6,
      "wall_time_s": 20.41464591026306
    },
    {
      "acc_task1_final": 0.083,
      "acc_task1_initial": 0.226,
      "arm": "baseline",
      "excluded_underperforming_baseline": false,
      "hp_combo_id": "C5",
      "recombine_strategy": "mog",
      "retention": 0.3672566371681416,
      "run_id": "d1cd21603eee1cbe658bdd2d4c657425",
      "seed": 7,
      "wall_time_s": 21.39350199699402
    },
    {
      "acc_task1_final": 0.098,
      "acc_task1_initial": 0.256,
      "arm": "baseline",
      "excluded_underperforming_baseline": false,
      "hp_combo_id": "C5",
      "recombine_strategy": "mog",
      "retention": 0.3828125,
      "run_id": "9d6cae23aee0d49c60417993d6799445",
      "seed": 8,
      "wall_time_s": 20.087925910949707
    },
    {
      "acc_task1_final": 0.089,
      "acc_task1_initial": 0.274,
      "arm": "baseline",
      "excluded_underperforming_baseline": false,
      "hp_combo_id": "C5",
      "recombine_strategy": "mog",
      "retention": 0.3248175182481751,
      "run_id": "9af4f9bc42d3f7266d0e6e63fe3a5bfa",
      "seed": 9,
      "wall_time_s": 19.883203744888306
    },
    {
      "acc_task1_final": 0.07,
      "acc_task1_initial": 0.239,
      "arm": "baseline",
      "excluded_underperforming_baseline": false,
      "hp_combo_id": "C5",
      "recombine_strategy": "mog",
      "retention": 0.29288702928870297,
      "run_id": "d0ee330cbd54594eb93b8a85df382d01",
      "seed": 10,
      "wall_time_s": 21.292357206344604
    },
    {
      "acc_task1_final": 0.083,
      "acc_task1_initial": 0.244,
      "arm": "baseline",
      "excluded_underperforming_baseline": false,
      "hp_combo_id": "C5",
      "recombine_strategy": "mog",
      "retention": 0.34016393442622955,
      "run_id": "8dfb6378195a95887f27a674a024edd4",
      "seed": 11,
      "wall_time_s": 20.24702215194702
    },
    {
      "acc_task1_final": 0.072,
      "acc_task1_initial": 0.206,
      "arm": "baseline",
      "excluded_underperforming_baseline": false,
      "hp_combo_id": "C5",
      "recombine_strategy": "mog",
      "retention": 0.34951456310679613,
      "run_id": "46a1f5a7a9ebd381c67c64a208ce5f76",
      "seed": 12,
      "wall_time_s": 20.04124617576599
    },
    {
      "acc_task1_final": 0.096,
      "acc_task1_initial": 0.212,
      "arm": "baseline",
      "excluded_underperforming_baseline": false,
      "hp_combo_id": "C5",
      "recombine_strategy": "mog",
      "retention": 0.4528301886792453,
      "run_id": "031285d595665235eabe4166c7e75909",
      "seed": 13,
      "wall_time_s": 20.957263231277466
    },
    {
      "acc_task1_final": 0.067,
      "acc_task1_initial": 0.24,
      "arm": "baseline",
      "excluded_underperforming_baseline": false,
      "hp_combo_id": "C5",
      "recombine_strategy": "mog",
      "retention": 0.2791666666666667,
      "run_id": "1c27e429e0ea1996f377b0c9dbb22411",
      "seed": 14,
      "wall_time_s": 19.000913858413696
    },
    {
      "acc_task1_final": 0.063,
      "acc_task1_initial": 0.253,
      "arm": "baseline",
      "excluded_underperforming_baseline": false,
      "hp_combo_id": "C5",
      "recombine_strategy": "mog",
      "retention": 0.2490118577075099,
      "run_id": "6f97ccfd3a8afce61aedc8e28437f96d",
      "seed": 15,
      "wall_time_s": 19.91099977493286
    },
    {
      "acc_task1_final": 0.084,
      "acc_task1_initial": 0.159,
      "arm": "baseline",
      "excluded_underperforming_baseline": true,
      "hp_combo_id": "C5",
      "recombine_strategy": "mog",
      "retention": 0.5283018867924528,
      "run_id": "87f5a42345b3ee66421d9c3fde10f273",
      "seed": 16,
      "wall_time_s": 20.051326990127563
    },
    {
      "acc_task1_final": 0.086,
      "acc_task1_initial": 0.197,
      "arm": "baseline",
      "excluded_underperforming_baseline": true,
      "hp_combo_id": "C5",
      "recombine_strategy": "mog",
      "retention": 0.43654822335025373,
      "run_id": "9e66199dce08a13c48f88ccca64b4912",
      "seed": 17,
      "wall_time_s": 19.52599573135376
    },
    {
      "acc_task1_final": 0.081,
      "acc_task1_initial": 0.24,
      "arm": "baseline",
      "excluded_underperforming_baseline": false,
      "hp_combo_id": "C5",
      "recombine_strategy": "mog",
      "retention": 0.3375,
      "run_id": "69e617e9ef6191028dba18b4a7da1b76",
      "seed": 18,
      "wall_time_s": 20.466655015945435
    },
    {
      "acc_task1_final": 0.069,
      "acc_task1_initial": 0.182,
      "arm": "baseline",
      "excluded_underperforming_baseline": true,
      "hp_combo_id": "C5",
      "recombine_strategy": "mog",
      "retention": 0.37912087912087916,
      "run_id": "bbb6d727d62cbc58d99c33a943fd1dcf",
      "seed": 19,
      "wall_time_s": 20.665929317474365
    },
    {
      "acc_task1_final": 0.091,
      "acc_task1_initial": 0.206,
      "arm": "baseline",
      "excluded_underperforming_baseline": false,
      "hp_combo_id": "C5",
      "recombine_strategy": "mog",
      "retention": 0.441747572815534,
      "run_id": "9a27f7a8936f477afe2798daab083e4f",
      "seed": 20,
      "wall_time_s": 19.58603596687317
    },
    {
      "acc_task1_final": 0.081,
      "acc_task1_initial": 0.234,
      "arm": "baseline",
      "excluded_underperforming_baseline": false,
      "hp_combo_id": "C5",
      "recombine_strategy": "mog",
      "retention": 0.34615384615384615,
      "run_id": "843b3c44c5a7b369f5d3e813ebe1bb3d",
      "seed": 21,
      "wall_time_s": 19.770874738693237
    },
    {
      "acc_task1_final": 0.102,
      "acc_task1_initial": 0.189,
      "arm": "baseline",
      "excluded_underperforming_baseline": true,
      "hp_combo_id": "C5",
      "recombine_strategy": "mog",
      "retention": 0.5396825396825397,
      "run_id": "e4665733d393dd29fd5ed835210d96b0",
      "seed": 22,
      "wall_time_s": 19.214568853378296
    },
    {
      "acc_task1_final": 0.108,
      "acc_task1_initial": 0.255,
      "arm": "baseline",
      "excluded_underperforming_baseline": false,
      "hp_combo_id": "C5",
      "recombine_strategy": "mog",
      "retention": 0.4235294117647059,
      "run_id": "18eecb302c133ef348e08429f55c37f0",
      "seed": 23,
      "wall_time_s": 19.52464199066162
    },
    {
      "acc_task1_final": 0.11,
      "acc_task1_initial": 0.22,
      "arm": "baseline",
      "excluded_underperforming_baseline": false,
      "hp_combo_id": "C5",
      "recombine_strategy": "mog",
      "retention": 0.5,
      "run_id": "fa86a78474bd651b5291daf3d3edc779",
      "seed": 24,
      "wall_time_s": 21.47179889678955
    },
    {
      "acc_task1_final": 0.09,
      "acc_task1_initial": 0.243,
      "arm": "baseline",
      "excluded_underperforming_baseline": false,
      "hp_combo_id": "C5",
      "recombine_strategy": "mog",
      "retention": 0.37037037037037035,
      "run_id": "c6146f64b14311968e3b5af4a0cf170a",
      "seed": 25,
      "wall_time_s": 21.460274934768677
    },
    {
      "acc_task1_final": 0.059,
      "acc_task1_initial": 0.298,
      "arm": "baseline",
      "excluded_underperforming_baseline": false,
      "hp_combo_id": "C5",
      "recombine_strategy": "mog",
      "retention": 0.19798657718120805,
      "run_id": "e04964e4acf53dca02191f5d1af6b6d7",
      "seed": 26,
      "wall_time_s": 20.377032041549683
    },
    {
      "acc_task1_final": 0.076,
      "acc_task1_initial": 0.146,
      "arm": "baseline",
      "excluded_underperforming_baseline": true,
      "hp_combo_id": "C5",
      "recombine_strategy": "mog",
      "retention": 0.5205479452054794,
      "run_id": "f2bafed1c559dad01c75247b6f05edef",
      "seed": 27,
      "wall_time_s": 20.313751935958862
    },
    {
      "acc_task1_final": 0.094,
      "acc_task1_initial": 0.171,
      "arm": "baseline",
      "excluded_underperforming_baseline": true,
      "hp_combo_id": "C5",
      "recombine_strategy": "mog",
      "retention": 0.5497076023391813,
      "run_id": "cc87ac608d047371dfdf0260512ee347",
      "seed": 28,
      "wall_time_s": 19.611292123794556
    },
    {
      "acc_task1_final": 0.113,
      "acc_task1_initial": 0.267,
      "arm": "baseline",
      "excluded_underperforming_baseline": false,
      "hp_combo_id": "C5",
      "recombine_strategy": "mog",
      "retention": 0.4232209737827715,
      "run_id": "aec2cbf6f8fd6a77b02a91c9ba379cba",
      "seed": 29,
      "wall_time_s": 19.176828145980835
    },
    {
      "acc_task1_final": 0.102,
      "acc_task1_initial": 0.188,
      "arm": "P_min",
      "excluded_underperforming_baseline": true,
      "hp_combo_id": "C5",
      "recombine_strategy": "mog",
      "retention": 0.5425531914893617,
      "run_id": "50dd237cda5bcc25aee47bd32c06d5c2",
      "seed": 0,
      "wall_time_s": 20.411340713500977
    },
    {
      "acc_task1_final": 0.048,
      "acc_task1_initial": 0.209,
      "arm": "P_min",
      "excluded_underperforming_baseline": false,
      "hp_combo_id": "C5",
      "recombine_strategy": "mog",
      "retention": 0.22966507177033493,
      "run_id": "69786277a21a50927e3dab73c3c61207",
      "seed": 1,
      "wall_time_s": 20.157424211502075
    },
    {
      "acc_task1_final": 0.095,
      "acc_task1_initial": 0.209,
      "arm": "P_min",
      "excluded_underperforming_baseline": false,
      "hp_combo_id": "C5",
      "recombine_strategy": "mog",
      "retention": 0.4545454545454546,
      "run_id": "0c8a8f0c00171f20a24618db4620117e",
      "seed": 2,
      "wall_time_s": 19.74215602874756
    },
    {
      "acc_task1_final": 0.094,
      "acc_task1_initial": 0.27,
      "arm": "P_min",
      "excluded_underperforming_baseline": false,
      "hp_combo_id": "C5",
      "recombine_strategy": "mog",
      "retention": 0.34814814814814815,
      "run_id": "0918b5989a6c4a66650d9fd890035dd7",
      "seed": 3,
      "wall_time_s": 20.09624195098877
    },
    {
      "acc_task1_final": 0.094,
      "acc_task1_initial": 0.268,
      "arm": "P_min",
      "excluded_underperforming_baseline": false,
      "hp_combo_id": "C5",
      "recombine_strategy": "mog",
      "retention": 0.3507462686567164,
      "run_id": "dfdbf7552c69c16efedab3f70bcdfc6e",
      "seed": 4,
      "wall_time_s": 20.125683069229126
    },
    {
      "acc_task1_final": 0.08,
      "acc_task1_initial": 0.238,
      "arm": "P_min",
      "excluded_underperforming_baseline": false,
      "hp_combo_id": "C5",
      "recombine_strategy": "mog",
      "retention": 0.33613445378151263,
      "run_id": "a726856db6f971bd10cebc1e2a5e6e52",
      "seed": 5,
      "wall_time_s": 20.772703886032104
    },
    {
      "acc_task1_final": 0.083,
      "acc_task1_initial": 0.247,
      "arm": "P_min",
      "excluded_underperforming_baseline": false,
      "hp_combo_id": "C5",
      "recombine_strategy": "mog",
      "retention": 0.3360323886639676,
      "run_id": "2ba48bdbcae11087a4bce35ac868a2e3",
      "seed": 6,
      "wall_time_s": 20.451663970947266
    },
    {
      "acc_task1_final": 0.068,
      "acc_task1_initial": 0.226,
      "arm": "P_min",
      "excluded_underperforming_baseline": false,
      "hp_combo_id": "C5",
      "recombine_strategy": "mog",
      "retention": 0.3008849557522124,
      "run_id": "e79b25748bd466b5100369297d87285c",
      "seed": 7,
      "wall_time_s": 20.006276845932007
    },
    {
      "acc_task1_final": 0.12,
      "acc_task1_initial": 0.256,
      "arm": "P_min",
      "excluded_underperforming_baseline": false,
      "hp_combo_id": "C5",
      "recombine_strategy": "mog",
      "retention": 0.46875,
      "run_id": "624668690d5e8d38fb906db78847e2a7",
      "seed": 8,
      "wall_time_s": 18.669808864593506
    },
    {
      "acc_task1_final": 0.085,
      "acc_task1_initial": 0.274,
      "arm": "P_min",
      "excluded_underperforming_baseline": false,
      "hp_combo_id": "C5",
      "recombine_strategy": "mog",
      "retention": 0.3102189781021898,
      "run_id": "5023e549763eec70086f7941019d5239",
      "seed": 9,
      "wall_time_s": 20.280169010162354
    },
    {
      "acc_task1_final": 0.073,
      "acc_task1_initial": 0.239,
      "arm": "P_min",
      "excluded_underperforming_baseline": false,
      "hp_combo_id": "C5",
      "recombine_strategy": "mog",
      "retention": 0.3054393305439331,
      "run_id": "7abce1a3b470f7ade1df45cb859624b4",
      "seed": 10,
      "wall_time_s": 20.225944995880127
    },
    {
      "acc_task1_final": 0.082,
      "acc_task1_initial": 0.244,
      "arm": "P_min",
      "excluded_underperforming_baseline": false,
      "hp_combo_id": "C5",
      "recombine_strategy": "mog",
      "retention": 0.33606557377049184,
      "run_id": "3949a62c46dd00f63734097d226216e1",
      "seed": 11,
      "wall_time_s": 21.00122904777527
    },
    {
      "acc_task1_final": 0.081,
      "acc_task1_initial": 0.206,
      "arm": "P_min",
      "excluded_underperforming_baseline": false,
      "hp_combo_id": "C5",
      "recombine_strategy": "mog",
      "retention": 0.3932038834951457,
      "run_id": "a3f710f91b0da6e71abf3d847a8f70e7",
      "seed": 12,
      "wall_time_s": 20.47630214691162
    },
    {
      "acc_task1_final": 0.098,
      "acc_task1_initial": 0.212,
      "arm": "P_min",
      "excluded_underperforming_baseline": false,
      "hp_combo_id": "C5",
      "recombine_strategy": "mog",
      "retention": 0.46226415094339623,
      "run_id": "7277b207dc6196a1d718c48cb61f95ea",
      "seed": 13,
      "wall_time_s": 20.65022587776184
    },
    {
      "acc_task1_final": 0.079,
      "acc_task1_initial": 0.24,
      "arm": "P_min",
      "excluded_underperforming_baseline": false,
      "hp_combo_id": "C5",
      "recombine_strategy": "mog",
      "retention": 0.32916666666666666,
      "run_id": "46e5299798bc3f6988a55734cc29534b",
      "seed": 14,
      "wall_time_s": 18.78016424179077
    },
    {
      "acc_task1_final": 0.065,
      "acc_task1_initial": 0.253,
      "arm": "P_min",
      "excluded_underperforming_baseline": false,
      "hp_combo_id": "C5",
      "recombine_strategy": "mog",
      "retention": 0.25691699604743085,
      "run_id": "094db81a73c48802c842da48c10bb515",
      "seed": 15,
      "wall_time_s": 20.481157064437866
    },
    {
      "acc_task1_final": 0.091,
      "acc_task1_initial": 0.159,
      "arm": "P_min",
      "excluded_underperforming_baseline": true,
      "hp_combo_id": "C5",
      "recombine_strategy": "mog",
      "retention": 0.5723270440251572,
      "run_id": "b2377a5f47593144e383441a85c741de",
      "seed": 16,
      "wall_time_s": 20.742511987686157
    },
    {
      "acc_task1_final": 0.12,
      "acc_task1_initial": 0.197,
      "arm": "P_min",
      "excluded_underperforming_baseline": true,
      "hp_combo_id": "C5",
      "recombine_strategy": "mog",
      "retention": 0.6091370558375634,
      "run_id": "561d4203fc9543b95a798ad9308388f0",
      "seed": 17,
      "wall_time_s": 19.38577175140381
    },
    {
      "acc_task1_final": 0.075,
      "acc_task1_initial": 0.24,
      "arm": "P_min",
      "excluded_underperforming_baseline": false,
      "hp_combo_id": "C5",
      "recombine_strategy": "mog",
      "retention": 0.3125,
      "run_id": "856f9bcb03a1315e5950a77427c4f302",
      "seed": 18,
      "wall_time_s": 20.18523907661438
    },
    {
      "acc_task1_final": 0.063,
      "acc_task1_initial": 0.182,
      "arm": "P_min",
      "excluded_underperforming_baseline": true,
      "hp_combo_id": "C5",
      "recombine_strategy": "mog",
      "retention": 0.34615384615384615,
      "run_id": "64cb9daee4ef14549bf15c488e491574",
      "seed": 19,
      "wall_time_s": 19.62805700302124
    },
    {
      "acc_task1_final": 0.096,
      "acc_task1_initial": 0.206,
      "arm": "P_min",
      "excluded_underperforming_baseline": false,
      "hp_combo_id": "C5",
      "recombine_strategy": "mog",
      "retention": 0.46601941747572817,
      "run_id": "3b4837d72d52752c1461a9dbafd3b978",
      "seed": 20,
      "wall_time_s": 19.94229006767273
    },
    {
      "acc_task1_final": 0.077,
      "acc_task1_initial": 0.234,
      "arm": "P_min",
      "excluded_underperforming_baseline": false,
      "hp_combo_id": "C5",
      "recombine_strategy": "mog",
      "retention": 0.32905982905982906,
      "run_id": "7c9acca3a780003dca0414c8272a635d",
      "seed": 21,
      "wall_time_s": 19.475773096084595
    },
    {
      "acc_task1_final": 0.109,
      "acc_task1_initial": 0.189,
      "arm": "P_min",
      "excluded_underperforming_baseline": true,
      "hp_combo_id": "C5",
      "recombine_strategy": "mog",
      "retention": 0.5767195767195767,
      "run_id": "a681879bec96e2cf8243feac841d339f",
      "seed": 22,
      "wall_time_s": 19.122376918792725
    },
    {
      "acc_task1_final": 0.116,
      "acc_task1_initial": 0.255,
      "arm": "P_min",
      "excluded_underperforming_baseline": false,
      "hp_combo_id": "C5",
      "recombine_strategy": "mog",
      "retention": 0.4549019607843137,
      "run_id": "9e87dff4e5d7986255a649d54bedf3dc",
      "seed": 23,
      "wall_time_s": 19.602288246154785
    },
    {
      "acc_task1_final": 0.09,
      "acc_task1_initial": 0.22,
      "arm": "P_min",
      "excluded_underperforming_baseline": false,
      "hp_combo_id": "C5",
      "recombine_strategy": "mog",
      "retention": 0.40909090909090906,
      "run_id": "2ad2799f7071d5ed9bf0f7dcbf79d52e",
      "seed": 24,
      "wall_time_s": 21.248777151107788
    },
    {
      "acc_task1_final": 0.094,
      "acc_task1_initial": 0.243,
      "arm": "P_min",
      "excluded_underperforming_baseline": false,
      "hp_combo_id": "C5",
      "recombine_strategy": "mog",
      "retention": 0.3868312757201646,
      "run_id": "88aa6bac2d6f965fa3d58cf2d31af481",
      "seed": 25,
      "wall_time_s": 20.176374197006226
    },
    {
      "acc_task1_final": 0.046,
      "acc_task1_initial": 0.298,
      "arm": "P_min",
      "excluded_underperforming_baseline": false,
      "hp_combo_id": "C5",
      "recombine_strategy": "mog",
      "retention": 0.15436241610738255,
      "run_id": "bec7226a5ef654d31f1d65ccd8b2b703",
      "seed": 26,
      "wall_time_s": 20.376259803771973
    },
    {
      "acc_task1_final": 0.07,
      "acc_task1_initial": 0.146,
      "arm": "P_min",
      "excluded_underperforming_baseline": true,
      "hp_combo_id": "C5",
      "recombine_strategy": "mog",
      "retention": 0.47945205479452063,
      "run_id": "c2c06d250be0ac366ffcd0c7eeed3ef0",
      "seed": 27,
      "wall_time_s": 19.827123165130615
    },
    {
      "acc_task1_final": 0.1,
      "acc_task1_initial": 0.171,
      "arm": "P_min",
      "excluded_underperforming_baseline": true,
      "hp_combo_id": "C5",
      "recombine_strategy": "mog",
      "retention": 0.5847953216374269,
      "run_id": "7bf346f5bf24263833eb1f0a6498b0fc",
      "seed": 28,
      "wall_time_s": 21.422816038131714
    },
    {
      "acc_task1_final": 0.127,
      "acc_task1_initial": 0.267,
      "arm": "P_min",
      "excluded_underperforming_baseline": false,
      "hp_combo_id": "C5",
      "recombine_strategy": "mog",
      "retention": 0.4756554307116105,
      "run_id": "f85be9abebffbfbda33cd910f9e7ca34",
      "seed": 29,
      "wall_time_s": 20.4308021068573
    },
    {
      "acc_task1_final": 0.103,
      "acc_task1_initial": 0.188,
      "arm": "P_equ",
      "excluded_underperforming_baseline": true,
      "hp_combo_id": "C5",
      "recombine_strategy": "mog",
      "retention": 0.5478723404255319,
      "run_id": "e4c642a160df82bf35b9f56f7455307e",
      "seed": 0,
      "wall_time_s": 21.837294101715088
    },
    {
      "acc_task1_final": 0.068,
      "acc_task1_initial": 0.209,
      "arm": "P_equ",
      "excluded_underperforming_baseline": false,
      "hp_combo_id": "C5",
      "recombine_strategy": "mog",
      "retention": 0.3253588516746412,
      "run_id": "fc6070ed3a05a61f99294d6b096bfed0",
      "seed": 1,
      "wall_time_s": 21.736432790756226
    },
    {
      "acc_task1_final": 0.099,
      "acc_task1_initial": 0.209,
      "arm": "P_equ",
      "excluded_underperforming_baseline": false,
      "hp_combo_id": "C5",
      "recombine_strategy": "mog",
      "retention": 0.4736842105263158,
      "run_id": "7fb3fffb9c55be3e468fc2e4148fe2e1",
      "seed": 2,
      "wall_time_s": 23.18695092201233
    },
    {
      "acc_task1_final": 0.088,
      "acc_task1_initial": 0.27,
      "arm": "P_equ",
      "excluded_underperforming_baseline": false,
      "hp_combo_id": "C5",
      "recombine_strategy": "mog",
      "retention": 0.3259259259259259,
      "run_id": "7068f348fffabd54ab12f82e7f680b35",
      "seed": 3,
      "wall_time_s": 21.728266954421997
    },
    {
      "acc_task1_final": 0.103,
      "acc_task1_initial": 0.268,
      "arm": "P_equ",
      "excluded_underperforming_baseline": false,
      "hp_combo_id": "C5",
      "recombine_strategy": "mog",
      "retention": 0.38432835820895517,
      "run_id": "83c80269fb6813b0c0d4c38ac2c8f4b4",
      "seed": 4,
      "wall_time_s": 21.587097883224487
    },
    {
      "acc_task1_final": 0.066,
      "acc_task1_initial": 0.238,
      "arm": "P_equ",
      "excluded_underperforming_baseline": false,
      "hp_combo_id": "C5",
      "recombine_strategy": "mog",
      "retention": 0.2773109243697479,
      "run_id": "9dffcd65897fbc2cc53abcb76db469bf",
      "seed": 5,
      "wall_time_s": 19.731477975845337
    },
    {
      "acc_task1_final": 0.072,
      "acc_task1_initial": 0.247,
      "arm": "P_equ",
      "excluded_underperforming_baseline": false,
      "hp_combo_id": "C5",
      "recombine_strategy": "mog",
      "retention": 0.291497975708502,
      "run_id": "4309a7165eee84ec06546722b5c3409c",
      "seed": 6,
      "wall_time_s": 19.902790069580078
    },
    {
      "acc_task1_final": 0.073,
      "acc_task1_initial": 0.226,
      "arm": "P_equ",
      "excluded_underperforming_baseline": false,
      "hp_combo_id": "C5",
      "recombine_strategy": "mog",
      "retention": 0.32300884955752207,
      "run_id": "968ab3ff046f8ed61d33a5dd3c3938c7",
      "seed": 7,
      "wall_time_s": 19.793954133987427
    },
    {
      "acc_task1_final": 0.114,
      "acc_task1_initial": 0.256,
      "arm": "P_equ",
      "excluded_underperforming_baseline": false,
      "hp_combo_id": "C5",
      "recombine_strategy": "mog",
      "retention": 0.4453125,
      "run_id": "cb042f180ec27cab9779b711b566e216",
      "seed": 8,
      "wall_time_s": 19.844125032424927
    },
    {
      "acc_task1_final": 0.093,
      "acc_task1_initial": 0.274,
      "arm": "P_equ",
      "excluded_underperforming_baseline": false,
      "hp_combo_id": "C5",
      "recombine_strategy": "mog",
      "retention": 0.33941605839416056,
      "run_id": "ceeb18938d6749caa66a7a293e80bdbf",
      "seed": 9,
      "wall_time_s": 19.208391904830933
    },
    {
      "acc_task1_final": 0.08,
      "acc_task1_initial": 0.239,
      "arm": "P_equ",
      "excluded_underperforming_baseline": false,
      "hp_combo_id": "C5",
      "recombine_strategy": "mog",
      "retention": 0.3347280334728034,
      "run_id": "b30de077f1dc95b4e141130d1e903ef1",
      "seed": 10,
      "wall_time_s": 19.78130316734314
    },
    {
      "acc_task1_final": 0.076,
      "acc_task1_initial": 0.244,
      "arm": "P_equ",
      "excluded_underperforming_baseline": false,
      "hp_combo_id": "C5",
      "recombine_strategy": "mog",
      "retention": 0.3114754098360656,
      "run_id": "d2a29bed855fe4b9426250054c878d17",
      "seed": 11,
      "wall_time_s": 19.07270097732544
    },
    {
      "acc_task1_final": 0.082,
      "acc_task1_initial": 0.206,
      "arm": "P_equ",
      "excluded_underperforming_baseline": false,
      "hp_combo_id": "C5",
      "recombine_strategy": "mog",
      "retention": 0.3980582524271845,
      "run_id": "f0c8f4edca67c60f20daf1ba31ab5064",
      "seed": 12,
      "wall_time_s": 19.44682812690735
    },
    {
      "acc_task1_final": 0.101,
      "acc_task1_initial": 0.212,
      "arm": "P_equ",
      "excluded_underperforming_baseline": false,
      "hp_combo_id": "C5",
      "recombine_strategy": "mog",
      "retention": 0.4764150943396227,
      "run_id": "aba8e48c0a652369bd44323e01d92d5f",
      "seed": 13,
      "wall_time_s": 19.922770977020264
    },
    {
      "acc_task1_final": 0.093,
      "acc_task1_initial": 0.24,
      "arm": "P_equ",
      "excluded_underperforming_baseline": false,
      "hp_combo_id": "C5",
      "recombine_strategy": "mog",
      "retention": 0.3875,
      "run_id": "42935fc62d5c6f93c99fd3ffe84d8c12",
      "seed": 14,
      "wall_time_s": 20.191872119903564
    },
    {
      "acc_task1_final": 0.063,
      "acc_task1_initial": 0.253,
      "arm": "P_equ",
      "excluded_underperforming_baseline": false,
      "hp_combo_id": "C5",
      "recombine_strategy": "mog",
      "retention": 0.2490118577075099,
      "run_id": "03ec04f1bae27c2a12fb8af0af8df5df",
      "seed": 15,
      "wall_time_s": 20.15203881263733
    },
    {
      "acc_task1_final": 0.1,
      "acc_task1_initial": 0.159,
      "arm": "P_equ",
      "excluded_underperforming_baseline": true,
      "hp_combo_id": "C5",
      "recombine_strategy": "mog",
      "retention": 0.6289308176100629,
      "run_id": "d1699e83e4ada669bfb0f1b9167736c9",
      "seed": 16,
      "wall_time_s": 20.550533056259155
    },
    {
      "acc_task1_final": 0.104,
      "acc_task1_initial": 0.197,
      "arm": "P_equ",
      "excluded_underperforming_baseline": true,
      "hp_combo_id": "C5",
      "recombine_strategy": "mog",
      "retention": 0.5279187817258882,
      "run_id": "9742509e18b7d0e4ad16db6085f29415",
      "seed": 17,
      "wall_time_s": 19.8905987739563
    },
    {
      "acc_task1_final": 0.089,
      "acc_task1_initial": 0.24,
      "arm": "P_equ",
      "excluded_underperforming_baseline": false,
      "hp_combo_id": "C5",
      "recombine_strategy": "mog",
      "retention": 0.37083333333333335,
      "run_id": "e8a4b87f6dfc2a18f45a6a318250491b",
      "seed": 18,
      "wall_time_s": 19.44175410270691
    },
    {
      "acc_task1_final": 0.073,
      "acc_task1_initial": 0.182,
      "arm": "P_equ",
      "excluded_underperforming_baseline": true,
      "hp_combo_id": "C5",
      "recombine_strategy": "mog",
      "retention": 0.40109890109890106,
      "run_id": "01a60e5bd3fdc31340d4abaa6dab235e",
      "seed": 19,
      "wall_time_s": 19.266978979110718
    },
    {
      "acc_task1_final": 0.081,
      "acc_task1_initial": 0.206,
      "arm": "P_equ",
      "excluded_underperforming_baseline": false,
      "hp_combo_id": "C5",
      "recombine_strategy": "mog",
      "retention": 0.3932038834951457,
      "run_id": "a92666ff68e43d290a6f4c7f3888ba7a",
      "seed": 20,
      "wall_time_s": 19.953727960586548
    },
    {
      "acc_task1_final": 0.078,
      "acc_task1_initial": 0.234,
      "arm": "P_equ",
      "excluded_underperforming_baseline": false,
      "hp_combo_id": "C5",
      "recombine_strategy": "mog",
      "retention": 0.3333333333333333,
      "run_id": "d04916a8bd2f545f4bd8653bba7748e5",
      "seed": 21,
      "wall_time_s": 21.52594518661499
    },
    {
      "acc_task1_final": 0.097,
      "acc_task1_initial": 0.189,
      "arm": "P_equ",
      "excluded_underperforming_baseline": true,
      "hp_combo_id": "C5",
      "recombine_strategy": "mog",
      "retention": 0.5132275132275133,
      "run_id": "94998e4ca07549cba61abe16bd8ef239",
      "seed": 22,
      "wall_time_s": 19.195557117462158
    },
    {
      "acc_task1_final": 0.109,
      "acc_task1_initial": 0.255,
      "arm": "P_equ",
      "excluded_underperforming_baseline": false,
      "hp_combo_id": "C5",
      "recombine_strategy": "mog",
      "retention": 0.42745098039215684,
      "run_id": "d7feddb58bd3a567a37f47c28dce0a84",
      "seed": 23,
      "wall_time_s": 21.407129287719727
    },
    {
      "acc_task1_final": 0.093,
      "acc_task1_initial": 0.22,
      "arm": "P_equ",
      "excluded_underperforming_baseline": false,
      "hp_combo_id": "C5",
      "recombine_strategy": "mog",
      "retention": 0.42272727272727273,
      "run_id": "2116afaec74a5f7cc40eb7c1c8dceb13",
      "seed": 24,
      "wall_time_s": 20.764991998672485
    },
    {
      "acc_task1_final": 0.09,
      "acc_task1_initial": 0.243,
      "arm": "P_equ",
      "excluded_underperforming_baseline": false,
      "hp_combo_id": "C5",
      "recombine_strategy": "mog",
      "retention": 0.37037037037037035,
      "run_id": "e840c9ca2dc7f1c6397cfc97c6235a0f",
      "seed": 25,
      "wall_time_s": 18.086463928222656
    },
    {
      "acc_task1_final": 0.06,
      "acc_task1_initial": 0.298,
      "arm": "P_equ",
      "excluded_underperforming_baseline": false,
      "hp_combo_id": "C5",
      "recombine_strategy": "mog",
      "retention": 0.20134228187919465,
      "run_id": "7ec516ead19909b17e0d3ace4178464b",
      "seed": 26,
      "wall_time_s": 22.80125594139099
    },
    {
      "acc_task1_final": 0.071,
      "acc_task1_initial": 0.146,
      "arm": "P_equ",
      "excluded_underperforming_baseline": true,
      "hp_combo_id": "C5",
      "recombine_strategy": "mog",
      "retention": 0.4863013698630137,
      "run_id": "4d43b846a15844abb05e3a45d29b55cd",
      "seed": 27,
      "wall_time_s": 20.264044046401978
    },
    {
      "acc_task1_final": 0.1,
      "acc_task1_initial": 0.171,
      "arm": "P_equ",
      "excluded_underperforming_baseline": true,
      "hp_combo_id": "C5",
      "recombine_strategy": "mog",
      "retention": 0.5847953216374269,
      "run_id": "a60c673753d5a0337cf9fb123871812f",
      "seed": 28,
      "wall_time_s": 19.30981993675232
    },
    {
      "acc_task1_final": 0.125,
      "acc_task1_initial": 0.267,
      "arm": "P_equ",
      "excluded_underperforming_baseline": false,
      "hp_combo_id": "C5",
      "recombine_strategy": "mog",
      "retention": 0.4681647940074906,
      "run_id": "3457c83fb1ea343db7907db473e3872c",
      "seed": 29,
      "wall_time_s": 16.99746298789978
    },
    {
      "acc_task1_final": 0.103,
      "acc_task1_initial": 0.188,
      "arm": "P_max",
      "excluded_underperforming_baseline": true,
      "hp_combo_id": "C5",
      "recombine_strategy": "mog",
      "retention": 0.5478723404255319,
      "run_id": "d2b74002b25effb7198cef1728401134",
      "seed": 0,
      "wall_time_s": 20.22291088104248
    },
    {
      "acc_task1_final": 0.068,
      "acc_task1_initial": 0.209,
      "arm": "P_max",
      "excluded_underperforming_baseline": false,
      "hp_combo_id": "C5",
      "recombine_strategy": "mog",
      "retention": 0.3253588516746412,
      "run_id": "cfa08a5de9f1d26f3b8c6e709ac8b21b",
      "seed": 1,
      "wall_time_s": 19.320019006729126
    },
    {
      "acc_task1_final": 0.099,
      "acc_task1_initial": 0.209,
      "arm": "P_max",
      "excluded_underperforming_baseline": false,
      "hp_combo_id": "C5",
      "recombine_strategy": "mog",
      "retention": 0.4736842105263158,
      "run_id": "a6a3ed1b93490330fe918d003ae50b82",
      "seed": 2,
      "wall_time_s": 18.464831829071045
    },
    {
      "acc_task1_final": 0.088,
      "acc_task1_initial": 0.27,
      "arm": "P_max",
      "excluded_underperforming_baseline": false,
      "hp_combo_id": "C5",
      "recombine_strategy": "mog",
      "retention": 0.3259259259259259,
      "run_id": "44f3ef76a7838c7161e97c791063cc33",
      "seed": 3,
      "wall_time_s": 20.486194133758545
    },
    {
      "acc_task1_final": 0.103,
      "acc_task1_initial": 0.268,
      "arm": "P_max",
      "excluded_underperforming_baseline": false,
      "hp_combo_id": "C5",
      "recombine_strategy": "mog",
      "retention": 0.38432835820895517,
      "run_id": "11ee0a0035bf6a48193fd3b734fb336e",
      "seed": 4,
      "wall_time_s": 21.56533408164978
    },
    {
      "acc_task1_final": 0.066,
      "acc_task1_initial": 0.238,
      "arm": "P_max",
      "excluded_underperforming_baseline": false,
      "hp_combo_id": "C5",
      "recombine_strategy": "mog",
      "retention": 0.2773109243697479,
      "run_id": "db4f851ad48a8eb68eb9295048cb2966",
      "seed": 5,
      "wall_time_s": 20.16275405883789
    },
    {
      "acc_task1_final": 0.072,
      "acc_task1_initial": 0.247,
      "arm": "P_max",
      "excluded_underperforming_baseline": false,
      "hp_combo_id": "C5",
      "recombine_strategy": "mog",
      "retention": 0.291497975708502,
      "run_id": "78338da2d207cd03a9b831578278377c",
      "seed": 6,
      "wall_time_s": 20.356873989105225
    },
    {
      "acc_task1_final": 0.073,
      "acc_task1_initial": 0.226,
      "arm": "P_max",
      "excluded_underperforming_baseline": false,
      "hp_combo_id": "C5",
      "recombine_strategy": "mog",
      "retention": 0.32300884955752207,
      "run_id": "5d3da08bb8359acc447d8b0ab08cea4e",
      "seed": 7,
      "wall_time_s": 20.096111059188843
    },
    {
      "acc_task1_final": 0.114,
      "acc_task1_initial": 0.256,
      "arm": "P_max",
      "excluded_underperforming_baseline": false,
      "hp_combo_id": "C5",
      "recombine_strategy": "mog",
      "retention": 0.4453125,
      "run_id": "aa1d642498d696486d73d55ca59d9c58",
      "seed": 8,
      "wall_time_s": 21.63659906387329
    },
    {
      "acc_task1_final": 0.093,
      "acc_task1_initial": 0.274,
      "arm": "P_max",
      "excluded_underperforming_baseline": false,
      "hp_combo_id": "C5",
      "recombine_strategy": "mog",
      "retention": 0.33941605839416056,
      "run_id": "efc58a1952d49ba09014f0ae0a5df0bc",
      "seed": 9,
      "wall_time_s": 30.613133192062378
    },
    {
      "acc_task1_final": 0.08,
      "acc_task1_initial": 0.239,
      "arm": "P_max",
      "excluded_underperforming_baseline": false,
      "hp_combo_id": "C5",
      "recombine_strategy": "mog",
      "retention": 0.3347280334728034,
      "run_id": "9d02137e21f25373f3f785f3ff9831ee",
      "seed": 10,
      "wall_time_s": 27.82758378982544
    },
    {
      "acc_task1_final": 0.076,
      "acc_task1_initial": 0.244,
      "arm": "P_max",
      "excluded_underperforming_baseline": false,
      "hp_combo_id": "C5",
      "recombine_strategy": "mog",
      "retention": 0.3114754098360656,
      "run_id": "388a3acdb80a2a3a5a5d2d1ece75a772",
      "seed": 11,
      "wall_time_s": 22.881096839904785
    },
    {
      "acc_task1_final": 0.082,
      "acc_task1_initial": 0.206,
      "arm": "P_max",
      "excluded_underperforming_baseline": false,
      "hp_combo_id": "C5",
      "recombine_strategy": "mog",
      "retention": 0.3980582524271845,
      "run_id": "3a72ea3ddbcfe6fb7df45aef166d77af",
      "seed": 12,
      "wall_time_s": 19.223016262054443
    },
    {
      "acc_task1_final": 0.101,
      "acc_task1_initial": 0.212,
      "arm": "P_max",
      "excluded_underperforming_baseline": false,
      "hp_combo_id": "C5",
      "recombine_strategy": "mog",
      "retention": 0.4764150943396227,
      "run_id": "a0af449192917dccad02bb6c7eae3fbc",
      "seed": 13,
      "wall_time_s": 26.27379012107849
    },
    {
      "acc_task1_final": 0.093,
      "acc_task1_initial": 0.24,
      "arm": "P_max",
      "excluded_underperforming_baseline": false,
      "hp_combo_id": "C5",
      "recombine_strategy": "mog",
      "retention": 0.3875,
      "run_id": "0205808cd125c218fdd549a7f7dea13a",
      "seed": 14,
      "wall_time_s": 25.866675853729248
    },
    {
      "acc_task1_final": 0.063,
      "acc_task1_initial": 0.253,
      "arm": "P_max",
      "excluded_underperforming_baseline": false,
      "hp_combo_id": "C5",
      "recombine_strategy": "mog",
      "retention": 0.2490118577075099,
      "run_id": "22906d6a684187817ed70038ace90d1c",
      "seed": 15,
      "wall_time_s": 28.09282898902893
    },
    {
      "acc_task1_final": 0.1,
      "acc_task1_initial": 0.159,
      "arm": "P_max",
      "excluded_underperforming_baseline": true,
      "hp_combo_id": "C5",
      "recombine_strategy": "mog",
      "retention": 0.6289308176100629,
      "run_id": "7edf42c38173df7d6b030be165282ff9",
      "seed": 16,
      "wall_time_s": 28.532055139541626
    },
    {
      "acc_task1_final": 0.104,
      "acc_task1_initial": 0.197,
      "arm": "P_max",
      "excluded_underperforming_baseline": true,
      "hp_combo_id": "C5",
      "recombine_strategy": "mog",
      "retention": 0.5279187817258882,
      "run_id": "a0eb9f33bfbcad796a35f35b0fcd3781",
      "seed": 17,
      "wall_time_s": 26.795475959777832
    },
    {
      "acc_task1_final": 0.089,
      "acc_task1_initial": 0.24,
      "arm": "P_max",
      "excluded_underperforming_baseline": false,
      "hp_combo_id": "C5",
      "recombine_strategy": "mog",
      "retention": 0.37083333333333335,
      "run_id": "4850020150ff65ee70370961600af303",
      "seed": 18,
      "wall_time_s": 26.71479105949402
    },
    {
      "acc_task1_final": 0.073,
      "acc_task1_initial": 0.182,
      "arm": "P_max",
      "excluded_underperforming_baseline": true,
      "hp_combo_id": "C5",
      "recombine_strategy": "mog",
      "retention": 0.40109890109890106,
      "run_id": "6bede428873544cf3149ace57f154e6f",
      "seed": 19,
      "wall_time_s": 25.586533784866333
    },
    {
      "acc_task1_final": 0.081,
      "acc_task1_initial": 0.206,
      "arm": "P_max",
      "excluded_underperforming_baseline": false,
      "hp_combo_id": "C5",
      "recombine_strategy": "mog",
      "retention": 0.3932038834951457,
      "run_id": "ca4508c5df964510ae0172dc754865af",
      "seed": 20,
      "wall_time_s": 29.126366138458252
    },
    {
      "acc_task1_final": 0.078,
      "acc_task1_initial": 0.234,
      "arm": "P_max",
      "excluded_underperforming_baseline": false,
      "hp_combo_id": "C5",
      "recombine_strategy": "mog",
      "retention": 0.3333333333333333,
      "run_id": "36c943f17552c47d2de2237ae6757102",
      "seed": 21,
      "wall_time_s": 21.571521043777466
    },
    {
      "acc_task1_final": 0.097,
      "acc_task1_initial": 0.189,
      "arm": "P_max",
      "excluded_underperforming_baseline": true,
      "hp_combo_id": "C5",
      "recombine_strategy": "mog",
      "retention": 0.5132275132275133,
      "run_id": "e405e804d5f1387f78f8009175098593",
      "seed": 22,
      "wall_time_s": 18.418411016464233
    },
    {
      "acc_task1_final": 0.109,
      "acc_task1_initial": 0.255,
      "arm": "P_max",
      "excluded_underperforming_baseline": false,
      "hp_combo_id": "C5",
      "recombine_strategy": "mog",
      "retention": 0.42745098039215684,
      "run_id": "a1fcdcab82f7f14eda7be2091144eb70",
      "seed": 23,
      "wall_time_s": 20.959196090698242
    },
    {
      "acc_task1_final": 0.093,
      "acc_task1_initial": 0.22,
      "arm": "P_max",
      "excluded_underperforming_baseline": false,
      "hp_combo_id": "C5",
      "recombine_strategy": "mog",
      "retention": 0.42272727272727273,
      "run_id": "486cf44d307eab20f4836b2710dbb0ac",
      "seed": 24,
      "wall_time_s": 21.705209970474243
    },
    {
      "acc_task1_final": 0.09,
      "acc_task1_initial": 0.243,
      "arm": "P_max",
      "excluded_underperforming_baseline": false,
      "hp_combo_id": "C5",
      "recombine_strategy": "mog",
      "retention": 0.37037037037037035,
      "run_id": "5124da87c2fd8ce833f50774d680a3ad",
      "seed": 25,
      "wall_time_s": 27.85492706298828
    },
    {
      "acc_task1_final": 0.06,
      "acc_task1_initial": 0.298,
      "arm": "P_max",
      "excluded_underperforming_baseline": false,
      "hp_combo_id": "C5",
      "recombine_strategy": "mog",
      "retention": 0.20134228187919465,
      "run_id": "00541ea8c8a5e66935261b98378a8483",
      "seed": 26,
      "wall_time_s": 22.09332799911499
    },
    {
      "acc_task1_final": 0.071,
      "acc_task1_initial": 0.146,
      "arm": "P_max",
      "excluded_underperforming_baseline": true,
      "hp_combo_id": "C5",
      "recombine_strategy": "mog",
      "retention": 0.4863013698630137,
      "run_id": "a074ab037bf055bbd774ffd0772df489",
      "seed": 27,
      "wall_time_s": 21.881681203842163
    },
    {
      "acc_task1_final": 0.1,
      "acc_task1_initial": 0.171,
      "arm": "P_max",
      "excluded_underperforming_baseline": true,
      "hp_combo_id": "C5",
      "recombine_strategy": "mog",
      "retention": 0.5847953216374269,
      "run_id": "2b02fc1d480c88e91a08b03be972c3a8",
      "seed": 28,
      "wall_time_s": 26.081891775131226
    },
    {
      "acc_task1_final": 0.125,
      "acc_task1_initial": 0.267,
      "arm": "P_max",
      "excluded_underperforming_baseline": false,
      "hp_combo_id": "C5",
      "recombine_strategy": "mog",
      "retention": 0.4681647940074906,
      "run_id": "27dbc9ecc93cbd1eb673e7da054036e9",
      "seed": 29,
      "wall_time_s": 23.558043956756592
    },
    {
      "acc_task1_final": 0.094,
      "acc_task1_initial": 0.188,
      "arm": "baseline",
      "excluded_underperforming_baseline": true,
      "hp_combo_id": "C5",
      "recombine_strategy": "none",
      "retention": 0.5,
      "run_id": "9fabefa909a718866c4b8cd6f7d8aad2",
      "seed": 0,
      "wall_time_s": 20.24042534828186
    },
    {
      "acc_task1_final": 0.064,
      "acc_task1_initial": 0.209,
      "arm": "baseline",
      "excluded_underperforming_baseline": false,
      "hp_combo_id": "C5",
      "recombine_strategy": "none",
      "retention": 0.30622009569377995,
      "run_id": "82e8879721fcc1ebedf27456cafe98c1",
      "seed": 1,
      "wall_time_s": 17.46350121498108
    },
    {
      "acc_task1_final": 0.107,
      "acc_task1_initial": 0.209,
      "arm": "baseline",
      "excluded_underperforming_baseline": false,
      "hp_combo_id": "C5",
      "recombine_strategy": "none",
      "retention": 0.5119617224880383,
      "run_id": "7c4efb02268386ef45fd3792fb1bba00",
      "seed": 2,
      "wall_time_s": 27.295217752456665
    },
    {
      "acc_task1_final": 0.079,
      "acc_task1_initial": 0.27,
      "arm": "baseline",
      "excluded_underperforming_baseline": false,
      "hp_combo_id": "C5",
      "recombine_strategy": "none",
      "retention": 0.29259259259259257,
      "run_id": "e162b68409c2d38450e77b3be4e7298a",
      "seed": 3,
      "wall_time_s": 29.14791703224182
    },
    {
      "acc_task1_final": 0.083,
      "acc_task1_initial": 0.268,
      "arm": "baseline",
      "excluded_underperforming_baseline": false,
      "hp_combo_id": "C5",
      "recombine_strategy": "none",
      "retention": 0.30970149253731344,
      "run_id": "80fb3b153bb6e40644808b6eea3603b1",
      "seed": 4,
      "wall_time_s": 29.301380157470703
    },
    {
      "acc_task1_final": 0.073,
      "acc_task1_initial": 0.238,
      "arm": "baseline",
      "excluded_underperforming_baseline": false,
      "hp_combo_id": "C5",
      "recombine_strategy": "none",
      "retention": 0.3067226890756303,
      "run_id": "e5ddb4c2a75ffd89a07d8507d9c8b741",
      "seed": 5,
      "wall_time_s": 29.954960823059082
    },
    {
      "acc_task1_final": 0.082,
      "acc_task1_initial": 0.247,
      "arm": "baseline",
      "excluded_underperforming_baseline": false,
      "hp_combo_id": "C5",
      "recombine_strategy": "none",
      "retention": 0.3319838056680162,
      "run_id": "02a0130c8e68eec0354ad10bd3dbeb22",
      "seed": 6,
      "wall_time_s": 18.610841751098633
    },
    {
      "acc_task1_final": 0.083,
      "acc_task1_initial": 0.226,
      "arm": "baseline",
      "excluded_underperforming_baseline": false,
      "hp_combo_id": "C5",
      "recombine_strategy": "none",
      "retention": 0.3672566371681416,
      "run_id": "abf552160eb8f9b5b2a61aeca6c7bb1e",
      "seed": 7,
      "wall_time_s": 23.98361301422119
    },
    {
      "acc_task1_final": 0.098,
      "acc_task1_initial": 0.256,
      "arm": "baseline",
      "excluded_underperforming_baseline": false,
      "hp_combo_id": "C5",
      "recombine_strategy": "none",
      "retention": 0.3828125,
      "run_id": "97b2a9ea87c391ed5d57a1bc14f49d04",
      "seed": 8,
      "wall_time_s": 22.218980073928833
    },
    {
      "acc_task1_final": 0.089,
      "acc_task1_initial": 0.274,
      "arm": "baseline",
      "excluded_underperforming_baseline": false,
      "hp_combo_id": "C5",
      "recombine_strategy": "none",
      "retention": 0.3248175182481751,
      "run_id": "4bf014d16ec2cb402bedbf9c89b69285",
      "seed": 9,
      "wall_time_s": 18.874362230300903
    },
    {
      "acc_task1_final": 0.07,
      "acc_task1_initial": 0.239,
      "arm": "baseline",
      "excluded_underperforming_baseline": false,
      "hp_combo_id": "C5",
      "recombine_strategy": "none",
      "retention": 0.29288702928870297,
      "run_id": "0c5c046493e8e1a7fc0e7028d179e588",
      "seed": 10,
      "wall_time_s": 27.989200830459595
    },
    {
      "acc_task1_final": 0.083,
      "acc_task1_initial": 0.244,
      "arm": "baseline",
      "excluded_underperforming_baseline": false,
      "hp_combo_id": "C5",
      "recombine_strategy": "none",
      "retention": 0.34016393442622955,
      "run_id": "49373e3d13b6dd3fa7d2eea054a1902d",
      "seed": 11,
      "wall_time_s": 32.21191906929016
    },
    {
      "acc_task1_final": 0.072,
      "acc_task1_initial": 0.206,
      "arm": "baseline",
      "excluded_underperforming_baseline": false,
      "hp_combo_id": "C5",
      "recombine_strategy": "none",
      "retention": 0.34951456310679613,
      "run_id": "1494681cc85eaaca7cefa65e7ab78181",
      "seed": 12,
      "wall_time_s": 22.818023920059204
    },
    {
      "acc_task1_final": 0.096,
      "acc_task1_initial": 0.212,
      "arm": "baseline",
      "excluded_underperforming_baseline": false,
      "hp_combo_id": "C5",
      "recombine_strategy": "none",
      "retention": 0.4528301886792453,
      "run_id": "e52da8ff1165862caf34ab9a01358588",
      "seed": 13,
      "wall_time_s": 20.02276372909546
    },
    {
      "acc_task1_final": 0.067,
      "acc_task1_initial": 0.24,
      "arm": "baseline",
      "excluded_underperforming_baseline": false,
      "hp_combo_id": "C5",
      "recombine_strategy": "none",
      "retention": 0.2791666666666667,
      "run_id": "f7a2a910d0e5cc38e37d46c535fbe157",
      "seed": 14,
      "wall_time_s": 17.901689767837524
    },
    {
      "acc_task1_final": 0.063,
      "acc_task1_initial": 0.253,
      "arm": "baseline",
      "excluded_underperforming_baseline": false,
      "hp_combo_id": "C5",
      "recombine_strategy": "none",
      "retention": 0.2490118577075099,
      "run_id": "567c9d7ef1b08d4566ee5072fa6c3428",
      "seed": 15,
      "wall_time_s": 14.941154956817627
    },
    {
      "acc_task1_final": 0.084,
      "acc_task1_initial": 0.159,
      "arm": "baseline",
      "excluded_underperforming_baseline": true,
      "hp_combo_id": "C5",
      "recombine_strategy": "none",
      "retention": 0.5283018867924528,
      "run_id": "efe43bb82f275a7dc8f7a40cb9966ddb",
      "seed": 16,
      "wall_time_s": 23.183820009231567
    },
    {
      "acc_task1_final": 0.086,
      "acc_task1_initial": 0.197,
      "arm": "baseline",
      "excluded_underperforming_baseline": true,
      "hp_combo_id": "C5",
      "recombine_strategy": "none",
      "retention": 0.43654822335025373,
      "run_id": "1b66f1e4f9e057449b42fbf41122d064",
      "seed": 17,
      "wall_time_s": 25.67758297920227
    },
    {
      "acc_task1_final": 0.081,
      "acc_task1_initial": 0.24,
      "arm": "baseline",
      "excluded_underperforming_baseline": false,
      "hp_combo_id": "C5",
      "recombine_strategy": "none",
      "retention": 0.3375,
      "run_id": "11a7b81c8095fe77d53ec87704424e2d",
      "seed": 18,
      "wall_time_s": 24.654057025909424
    },
    {
      "acc_task1_final": 0.069,
      "acc_task1_initial": 0.182,
      "arm": "baseline",
      "excluded_underperforming_baseline": true,
      "hp_combo_id": "C5",
      "recombine_strategy": "none",
      "retention": 0.37912087912087916,
      "run_id": "ee5938781a9dba52597982925a7a6b52",
      "seed": 19,
      "wall_time_s": 18.365320920944214
    },
    {
      "acc_task1_final": 0.091,
      "acc_task1_initial": 0.206,
      "arm": "baseline",
      "excluded_underperforming_baseline": false,
      "hp_combo_id": "C5",
      "recombine_strategy": "none",
      "retention": 0.441747572815534,
      "run_id": "a78a1aeb9d64575b2891214bd6a0e1f4",
      "seed": 20,
      "wall_time_s": 15.908378839492798
    },
    {
      "acc_task1_final": 0.081,
      "acc_task1_initial": 0.234,
      "arm": "baseline",
      "excluded_underperforming_baseline": false,
      "hp_combo_id": "C5",
      "recombine_strategy": "none",
      "retention": 0.34615384615384615,
      "run_id": "2ccc491eeb41f466ec74b95f8a6197e7",
      "seed": 21,
      "wall_time_s": 15.569307804107666
    },
    {
      "acc_task1_final": 0.102,
      "acc_task1_initial": 0.189,
      "arm": "baseline",
      "excluded_underperforming_baseline": true,
      "hp_combo_id": "C5",
      "recombine_strategy": "none",
      "retention": 0.5396825396825397,
      "run_id": "f98a3554e8c83a5bcaa8df2207a4a870",
      "seed": 22,
      "wall_time_s": 16.04919409751892
    },
    {
      "acc_task1_final": 0.108,
      "acc_task1_initial": 0.255,
      "arm": "baseline",
      "excluded_underperforming_baseline": false,
      "hp_combo_id": "C5",
      "recombine_strategy": "none",
      "retention": 0.4235294117647059,
      "run_id": "dc082bfdc6f1698fba2cea0887472e72",
      "seed": 23,
      "wall_time_s": 21.065908908843994
    },
    {
      "acc_task1_final": 0.11,
      "acc_task1_initial": 0.22,
      "arm": "baseline",
      "excluded_underperforming_baseline": false,
      "hp_combo_id": "C5",
      "recombine_strategy": "none",
      "retention": 0.5,
      "run_id": "133601690ed6d0b8b3ae923dd22dd912",
      "seed": 24,
      "wall_time_s": 21.929061889648438
    },
    {
      "acc_task1_final": 0.09,
      "acc_task1_initial": 0.243,
      "arm": "baseline",
      "excluded_underperforming_baseline": false,
      "hp_combo_id": "C5",
      "recombine_strategy": "none",
      "retention": 0.37037037037037035,
      "run_id": "25ad53fd6955833716a49888ae0b9f16",
      "seed": 25,
      "wall_time_s": 26.002846002578735
    },
    {
      "acc_task1_final": 0.059,
      "acc_task1_initial": 0.298,
      "arm": "baseline",
      "excluded_underperforming_baseline": false,
      "hp_combo_id": "C5",
      "recombine_strategy": "none",
      "retention": 0.19798657718120805,
      "run_id": "e52fabbba8de4985d8629244bd556096",
      "seed": 26,
      "wall_time_s": 29.64399480819702
    },
    {
      "acc_task1_final": 0.076,
      "acc_task1_initial": 0.146,
      "arm": "baseline",
      "excluded_underperforming_baseline": true,
      "hp_combo_id": "C5",
      "recombine_strategy": "none",
      "retention": 0.5205479452054794,
      "run_id": "ed603dcebd048059f3b542100eac007a",
      "seed": 27,
      "wall_time_s": 20.351766109466553
    },
    {
      "acc_task1_final": 0.094,
      "acc_task1_initial": 0.171,
      "arm": "baseline",
      "excluded_underperforming_baseline": true,
      "hp_combo_id": "C5",
      "recombine_strategy": "none",
      "retention": 0.5497076023391813,
      "run_id": "d4dd0e3820cc2597ae4553ab440817de",
      "seed": 28,
      "wall_time_s": 22.300336122512817
    },
    {
      "acc_task1_final": 0.113,
      "acc_task1_initial": 0.267,
      "arm": "baseline",
      "excluded_underperforming_baseline": false,
      "hp_combo_id": "C5",
      "recombine_strategy": "none",
      "retention": 0.4232209737827715,
      "run_id": "81c3278a932a8f82f98fd9fc9e6fc656",
      "seed": 29,
      "wall_time_s": 18.39220094680786
    },
    {
      "acc_task1_final": 0.102,
      "acc_task1_initial": 0.188,
      "arm": "P_min",
      "excluded_underperforming_baseline": true,
      "hp_combo_id": "C5",
      "recombine_strategy": "none",
      "retention": 0.5425531914893617,
      "run_id": "ad05f2d93fa36dcb32a381d54d99f599",
      "seed": 0,
      "wall_time_s": 17.52005887031555
    },
    {
      "acc_task1_final": 0.048,
      "acc_task1_initial": 0.209,
      "arm": "P_min",
      "excluded_underperforming_baseline": false,
      "hp_combo_id": "C5",
      "recombine_strategy": "none",
      "retention": 0.22966507177033493,
      "run_id": "e42f4bac64cae0496c15d258126e141b",
      "seed": 1,
      "wall_time_s": 15.038311243057251
    },
    {
      "acc_task1_final": 0.095,
      "acc_task1_initial": 0.209,
      "arm": "P_min",
      "excluded_underperforming_baseline": false,
      "hp_combo_id": "C5",
      "recombine_strategy": "none",
      "retention": 0.4545454545454546,
      "run_id": "d9e01aa300160a0528d269ebf624d947",
      "seed": 2,
      "wall_time_s": 15.627288818359375
    },
    {
      "acc_task1_final": 0.094,
      "acc_task1_initial": 0.27,
      "arm": "P_min",
      "excluded_underperforming_baseline": false,
      "hp_combo_id": "C5",
      "recombine_strategy": "none",
      "retention": 0.34814814814814815,
      "run_id": "7cff3c4313820fb6b7c2c864ce01843e",
      "seed": 3,
      "wall_time_s": 12.550270795822144
    },
    {
      "acc_task1_final": 0.094,
      "acc_task1_initial": 0.268,
      "arm": "P_min",
      "excluded_underperforming_baseline": false,
      "hp_combo_id": "C5",
      "recombine_strategy": "none",
      "retention": 0.3507462686567164,
      "run_id": "23bd92cafc986abd8a087b5f92930a4c",
      "seed": 4,
      "wall_time_s": 14.916435956954956
    },
    {
      "acc_task1_final": 0.08,
      "acc_task1_initial": 0.238,
      "arm": "P_min",
      "excluded_underperforming_baseline": false,
      "hp_combo_id": "C5",
      "recombine_strategy": "none",
      "retention": 0.33613445378151263,
      "run_id": "b3db7ec9b53750a9334ebc16a73333cf",
      "seed": 5,
      "wall_time_s": 16.788927793502808
    },
    {
      "acc_task1_final": 0.083,
      "acc_task1_initial": 0.247,
      "arm": "P_min",
      "excluded_underperforming_baseline": false,
      "hp_combo_id": "C5",
      "recombine_strategy": "none",
      "retention": 0.3360323886639676,
      "run_id": "930631135f422e4ffda51982ef5d6013",
      "seed": 6,
      "wall_time_s": 20.61352300643921
    },
    {
      "acc_task1_final": 0.068,
      "acc_task1_initial": 0.226,
      "arm": "P_min",
      "excluded_underperforming_baseline": false,
      "hp_combo_id": "C5",
      "recombine_strategy": "none",
      "retention": 0.3008849557522124,
      "run_id": "9fd5ecf1144ef7dc87426e38e826afaf",
      "seed": 7,
      "wall_time_s": 15.408828020095825
    },
    {
      "acc_task1_final": 0.12,
      "acc_task1_initial": 0.256,
      "arm": "P_min",
      "excluded_underperforming_baseline": false,
      "hp_combo_id": "C5",
      "recombine_strategy": "none",
      "retention": 0.46875,
      "run_id": "5ca313593d6db83e9f2157d7dd4af6bf",
      "seed": 8,
      "wall_time_s": 17.272706031799316
    },
    {
      "acc_task1_final": 0.085,
      "acc_task1_initial": 0.274,
      "arm": "P_min",
      "excluded_underperforming_baseline": false,
      "hp_combo_id": "C5",
      "recombine_strategy": "none",
      "retention": 0.3102189781021898,
      "run_id": "9ed055b938f1c7848b2a08aaf32b05a6",
      "seed": 9,
      "wall_time_s": 18.16473698616028
    },
    {
      "acc_task1_final": 0.073,
      "acc_task1_initial": 0.239,
      "arm": "P_min",
      "excluded_underperforming_baseline": false,
      "hp_combo_id": "C5",
      "recombine_strategy": "none",
      "retention": 0.3054393305439331,
      "run_id": "1cc2be17b586b136b606e54456b3dee4",
      "seed": 10,
      "wall_time_s": 21.340655088424683
    },
    {
      "acc_task1_final": 0.082,
      "acc_task1_initial": 0.244,
      "arm": "P_min",
      "excluded_underperforming_baseline": false,
      "hp_combo_id": "C5",
      "recombine_strategy": "none",
      "retention": 0.33606557377049184,
      "run_id": "f0a96112dc0876809c6836618293412d",
      "seed": 11,
      "wall_time_s": 19.37243103981018
    },
    {
      "acc_task1_final": 0.081,
      "acc_task1_initial": 0.206,
      "arm": "P_min",
      "excluded_underperforming_baseline": false,
      "hp_combo_id": "C5",
      "recombine_strategy": "none",
      "retention": 0.3932038834951457,
      "run_id": "9450bb44206f1c5e5661fee93183fbd7",
      "seed": 12,
      "wall_time_s": 18.693798303604126
    },
    {
      "acc_task1_final": 0.098,
      "acc_task1_initial": 0.212,
      "arm": "P_min",
      "excluded_underperforming_baseline": false,
      "hp_combo_id": "C5",
      "recombine_strategy": "none",
      "retention": 0.46226415094339623,
      "run_id": "b72ddec4c116742f595b2eaa6068afc9",
      "seed": 13,
      "wall_time_s": 20.102124214172363
    },
    {
      "acc_task1_final": 0.079,
      "acc_task1_initial": 0.24,
      "arm": "P_min",
      "excluded_underperforming_baseline": false,
      "hp_combo_id": "C5",
      "recombine_strategy": "none",
      "retention": 0.32916666666666666,
      "run_id": "c98e7496005bbac4e326d1ae7495b211",
      "seed": 14,
      "wall_time_s": 18.828452825546265
    },
    {
      "acc_task1_final": 0.065,
      "acc_task1_initial": 0.253,
      "arm": "P_min",
      "excluded_underperforming_baseline": false,
      "hp_combo_id": "C5",
      "recombine_strategy": "none",
      "retention": 0.25691699604743085,
      "run_id": "46c9dd77ab7a567e37a19454fa00d930",
      "seed": 15,
      "wall_time_s": 18.504892110824585
    },
    {
      "acc_task1_final": 0.091,
      "acc_task1_initial": 0.159,
      "arm": "P_min",
      "excluded_underperforming_baseline": true,
      "hp_combo_id": "C5",
      "recombine_strategy": "none",
      "retention": 0.5723270440251572,
      "run_id": "6146d0a5b9e561f940d3bd538f192419",
      "seed": 16,
      "wall_time_s": 18.34160590171814
    },
    {
      "acc_task1_final": 0.12,
      "acc_task1_initial": 0.197,
      "arm": "P_min",
      "excluded_underperforming_baseline": true,
      "hp_combo_id": "C5",
      "recombine_strategy": "none",
      "retention": 0.6091370558375634,
      "run_id": "ff59ba503e128005cec0ae66a2774a3f",
      "seed": 17,
      "wall_time_s": 16.629679918289185
    },
    {
      "acc_task1_final": 0.075,
      "acc_task1_initial": 0.24,
      "arm": "P_min",
      "excluded_underperforming_baseline": false,
      "hp_combo_id": "C5",
      "recombine_strategy": "none",
      "retention": 0.3125,
      "run_id": "9fc23a5f8d93817718e41b66f44240d1",
      "seed": 18,
      "wall_time_s": 20.827805757522583
    },
    {
      "acc_task1_final": 0.063,
      "acc_task1_initial": 0.182,
      "arm": "P_min",
      "excluded_underperforming_baseline": true,
      "hp_combo_id": "C5",
      "recombine_strategy": "none",
      "retention": 0.34615384615384615,
      "run_id": "24c8e039f7d534a730edc94be0f7921a",
      "seed": 19,
      "wall_time_s": 18.91105818748474
    },
    {
      "acc_task1_final": 0.096,
      "acc_task1_initial": 0.206,
      "arm": "P_min",
      "excluded_underperforming_baseline": false,
      "hp_combo_id": "C5",
      "recombine_strategy": "none",
      "retention": 0.46601941747572817,
      "run_id": "68e016063844e1494480b637b54cf981",
      "seed": 20,
      "wall_time_s": 16.36694598197937
    },
    {
      "acc_task1_final": 0.077,
      "acc_task1_initial": 0.234,
      "arm": "P_min",
      "excluded_underperforming_baseline": false,
      "hp_combo_id": "C5",
      "recombine_strategy": "none",
      "retention": 0.32905982905982906,
      "run_id": "b473d93648fce14c7040dfeb8024db08",
      "seed": 21,
      "wall_time_s": 16.79726505279541
    },
    {
      "acc_task1_final": 0.109,
      "acc_task1_initial": 0.189,
      "arm": "P_min",
      "excluded_underperforming_baseline": true,
      "hp_combo_id": "C5",
      "recombine_strategy": "none",
      "retention": 0.5767195767195767,
      "run_id": "8d3697137d045dd28083a5c7650139bb",
      "seed": 22,
      "wall_time_s": 20.05260419845581
    },
    {
      "acc_task1_final": 0.116,
      "acc_task1_initial": 0.255,
      "arm": "P_min",
      "excluded_underperforming_baseline": false,
      "hp_combo_id": "C5",
      "recombine_strategy": "none",
      "retention": 0.4549019607843137,
      "run_id": "13a200f2595426962c2b844b9fd82810",
      "seed": 23,
      "wall_time_s": 18.67166018486023
    },
    {
      "acc_task1_final": 0.09,
      "acc_task1_initial": 0.22,
      "arm": "P_min",
      "excluded_underperforming_baseline": false,
      "hp_combo_id": "C5",
      "recombine_strategy": "none",
      "retention": 0.40909090909090906,
      "run_id": "5a03d1b7651c74afac4e32aa3643aba0",
      "seed": 24,
      "wall_time_s": 16.040308952331543
    },
    {
      "acc_task1_final": 0.094,
      "acc_task1_initial": 0.243,
      "arm": "P_min",
      "excluded_underperforming_baseline": false,
      "hp_combo_id": "C5",
      "recombine_strategy": "none",
      "retention": 0.3868312757201646,
      "run_id": "188516b5ddd33aea54eb656e4abb005e",
      "seed": 25,
      "wall_time_s": 15.804957866668701
    },
    {
      "acc_task1_final": 0.046,
      "acc_task1_initial": 0.298,
      "arm": "P_min",
      "excluded_underperforming_baseline": false,
      "hp_combo_id": "C5",
      "recombine_strategy": "none",
      "retention": 0.15436241610738255,
      "run_id": "3191ea80dd7a7a188a984a11dacac79d",
      "seed": 26,
      "wall_time_s": 18.244002103805542
    },
    {
      "acc_task1_final": 0.07,
      "acc_task1_initial": 0.146,
      "arm": "P_min",
      "excluded_underperforming_baseline": true,
      "hp_combo_id": "C5",
      "recombine_strategy": "none",
      "retention": 0.47945205479452063,
      "run_id": "359252a19dfc68fc64d9b458f9d4c3e1",
      "seed": 27,
      "wall_time_s": 21.926046133041382
    },
    {
      "acc_task1_final": 0.1,
      "acc_task1_initial": 0.171,
      "arm": "P_min",
      "excluded_underperforming_baseline": true,
      "hp_combo_id": "C5",
      "recombine_strategy": "none",
      "retention": 0.5847953216374269,
      "run_id": "5d0c4d5ac0a55406b782b9bd115ffe7f",
      "seed": 28,
      "wall_time_s": 16.636902809143066
    },
    {
      "acc_task1_final": 0.127,
      "acc_task1_initial": 0.267,
      "arm": "P_min",
      "excluded_underperforming_baseline": false,
      "hp_combo_id": "C5",
      "recombine_strategy": "none",
      "retention": 0.4756554307116105,
      "run_id": "ddc807fd4d6cb63273b06b531284dc79",
      "seed": 29,
      "wall_time_s": 17.055769681930542
    },
    {
      "acc_task1_final": 0.097,
      "acc_task1_initial": 0.188,
      "arm": "P_equ",
      "excluded_underperforming_baseline": true,
      "hp_combo_id": "C5",
      "recombine_strategy": "none",
      "retention": 0.5159574468085106,
      "run_id": "283771cd274839610004bae39e43d43a",
      "seed": 0,
      "wall_time_s": 23.718961238861084
    },
    {
      "acc_task1_final": 0.076,
      "acc_task1_initial": 0.209,
      "arm": "P_equ",
      "excluded_underperforming_baseline": false,
      "hp_combo_id": "C5",
      "recombine_strategy": "none",
      "retention": 0.36363636363636365,
      "run_id": "8471da9bd03c6efe3f168a0b66a5b848",
      "seed": 1,
      "wall_time_s": 18.394334077835083
    },
    {
      "acc_task1_final": 0.096,
      "acc_task1_initial": 0.209,
      "arm": "P_equ",
      "excluded_underperforming_baseline": false,
      "hp_combo_id": "C5",
      "recombine_strategy": "none",
      "retention": 0.45933014354066987,
      "run_id": "24e0e01049fe611a58d53f863422aa0b",
      "seed": 2,
      "wall_time_s": 25.878380060195923
    },
    {
      "acc_task1_final": 0.08,
      "acc_task1_initial": 0.27,
      "arm": "P_equ",
      "excluded_underperforming_baseline": false,
      "hp_combo_id": "C5",
      "recombine_strategy": "none",
      "retention": 0.2962962962962963,
      "run_id": "c9d39b4697a263503cca7f7e5a86ad1b",
      "seed": 3,
      "wall_time_s": 28.21934413909912
    },
    {
      "acc_task1_final": 0.104,
      "acc_task1_initial": 0.268,
      "arm": "P_equ",
      "excluded_underperforming_baseline": false,
      "hp_combo_id": "C5",
      "recombine_strategy": "none",
      "retention": 0.38805970149253727,
      "run_id": "aca5abc41e517667dab0fe6642f18c85",
      "seed": 4,
      "wall_time_s": 23.574568033218384
    },
    {
      "acc_task1_final": 0.078,
      "acc_task1_initial": 0.238,
      "arm": "P_equ",
      "excluded_underperforming_baseline": false,
      "hp_combo_id": "C5",
      "recombine_strategy": "none",
      "retention": 0.3277310924369748,
      "run_id": "63f538b3c7b7df1fafd654eff214cf79",
      "seed": 5,
      "wall_time_s": 23.39063811302185
    },
    {
      "acc_task1_final": 0.091,
      "acc_task1_initial": 0.247,
      "arm": "P_equ",
      "excluded_underperforming_baseline": false,
      "hp_combo_id": "C5",
      "recombine_strategy": "none",
      "retention": 0.3684210526315789,
      "run_id": "b32b7af5ab96d51a76d92e2a22cdbfd3",
      "seed": 6,
      "wall_time_s": 28.450714826583862
    },
    {
      "acc_task1_final": 0.066,
      "acc_task1_initial": 0.226,
      "arm": "P_equ",
      "excluded_underperforming_baseline": false,
      "hp_combo_id": "C5",
      "recombine_strategy": "none",
      "retention": 0.2920353982300885,
      "run_id": "ad565da5020679b328e74e5524ca4f11",
      "seed": 7,
      "wall_time_s": 28.580482721328735
    },
    {
      "acc_task1_final": 0.109,
      "acc_task1_initial": 0.256,
      "arm": "P_equ",
      "excluded_underperforming_baseline": false,
      "hp_combo_id": "C5",
      "recombine_strategy": "none",
      "retention": 0.42578125,
      "run_id": "559f1b287676fe3d48e82ba246a272a7",
      "seed": 8,
      "wall_time_s": 28.551700115203857
    },
    {
      "acc_task1_final": 0.08,
      "acc_task1_initial": 0.274,
      "arm": "P_equ",
      "excluded_underperforming_baseline": false,
      "hp_combo_id": "C5",
      "recombine_strategy": "none",
      "retention": 0.291970802919708,
      "run_id": "1970130851a8758913636767303017e5",
      "seed": 9,
      "wall_time_s": 28.908469915390015
    },
    {
      "acc_task1_final": 0.086,
      "acc_task1_initial": 0.239,
      "arm": "P_equ",
      "excluded_underperforming_baseline": false,
      "hp_combo_id": "C5",
      "recombine_strategy": "none",
      "retention": 0.3598326359832636,
      "run_id": "3d2e727b18b59fbc7551e50ca99915cb",
      "seed": 10,
      "wall_time_s": 26.83529305458069
    },
    {
      "acc_task1_final": 0.082,
      "acc_task1_initial": 0.244,
      "arm": "P_equ",
      "excluded_underperforming_baseline": false,
      "hp_combo_id": "C5",
      "recombine_strategy": "none",
      "retention": 0.33606557377049184,
      "run_id": "20a4f02faa6bd89ea290f28403867fdb",
      "seed": 11,
      "wall_time_s": 27.535506010055542
    },
    {
      "acc_task1_final": 0.081,
      "acc_task1_initial": 0.206,
      "arm": "P_equ",
      "excluded_underperforming_baseline": false,
      "hp_combo_id": "C5",
      "recombine_strategy": "none",
      "retention": 0.3932038834951457,
      "run_id": "03dc518bc28b482cc7394bcee98d632f",
      "seed": 12,
      "wall_time_s": 28.4721577167511
    },
    {
      "acc_task1_final": 0.097,
      "acc_task1_initial": 0.212,
      "arm": "P_equ",
      "excluded_underperforming_baseline": false,
      "hp_combo_id": "C5",
      "recombine_strategy": "none",
      "retention": 0.45754716981132076,
      "run_id": "7588a2d9bdcbac522cd6456d2d07f741",
      "seed": 13,
      "wall_time_s": 27.97035813331604
    },
    {
      "acc_task1_final": 0.076,
      "acc_task1_initial": 0.24,
      "arm": "P_equ",
      "excluded_underperforming_baseline": false,
      "hp_combo_id": "C5",
      "recombine_strategy": "none",
      "retention": 0.31666666666666665,
      "run_id": "5d335ce27f7827f5daf72eae4b711daa",
      "seed": 14,
      "wall_time_s": 12.5983407497406
    },
    {
      "acc_task1_final": 0.062,
      "acc_task1_initial": 0.253,
      "arm": "P_equ",
      "excluded_underperforming_baseline": false,
      "hp_combo_id": "C5",
      "recombine_strategy": "none",
      "retention": 0.2450592885375494,
      "run_id": "b8984e0fe71753299511bd3087c1bfe5",
      "seed": 15,
      "wall_time_s": 10.988250970840454
    },
    {
      "acc_task1_final": 0.103,
      "acc_task1_initial": 0.159,
      "arm": "P_equ",
      "excluded_underperforming_baseline": true,
      "hp_combo_id": "C5",
      "recombine_strategy": "none",
      "retention": 0.6477987421383647,
      "run_id": "fd24cef3266b52780cac9af34c0ee688",
      "seed": 16,
      "wall_time_s": 11.782132148742676
    },
    {
      "acc_task1_final": 0.101,
      "acc_task1_initial": 0.197,
      "arm": "P_equ",
      "excluded_underperforming_baseline": true,
      "hp_combo_id": "C5",
      "recombine_strategy": "none",
      "retention": 0.5126903553299492,
      "run_id": "3dbb8cd1b44a9e508047807e4a8191c8",
      "seed": 17,
      "wall_time_s": 15.792109727859497
    },
    {
      "acc_task1_final": 0.078,
      "acc_task1_initial": 0.24,
      "arm": "P_equ",
      "excluded_underperforming_baseline": false,
      "hp_combo_id": "C5",
      "recombine_strategy": "none",
      "retention": 0.325,
      "run_id": "89f4bd44f5af56d5a4f99482c65e6cc2",
      "seed": 18,
      "wall_time_s": 27.008304119110107
    },
    {
      "acc_task1_final": 0.085,
      "acc_task1_initial": 0.182,
      "arm": "P_equ",
      "excluded_underperforming_baseline": true,
      "hp_combo_id": "C5",
      "recombine_strategy": "none",
      "retention": 0.4670329670329671,
      "run_id": "f97f4c03a1ce8210e20bd9b77a25d9a0",
      "seed": 19,
      "wall_time_s": 28.84347629547119
    },
    {
      "acc_task1_final": 0.083,
      "acc_task1_initial": 0.206,
      "arm": "P_equ",
      "excluded_underperforming_baseline": false,
      "hp_combo_id": "C5",
      "recombine_strategy": "none",
      "retention": 0.40291262135922334,
      "run_id": "82bf9b8ebc94c547866f256c6f6ea8d5",
      "seed": 20,
      "wall_time_s": 27.698580026626587
    },
    {
      "acc_task1_final": 0.082,
      "acc_task1_initial": 0.234,
      "arm": "P_equ",
      "excluded_underperforming_baseline": false,
      "hp_combo_id": "C5",
      "recombine_strategy": "none",
      "retention": 0.3504273504273504,
      "run_id": "25c8e394772f70238031033b1ff46f30",
      "seed": 21,
      "wall_time_s": 28.616581916809082
    },
    {
      "acc_task1_final": 0.107,
      "acc_task1_initial": 0.189,
      "arm": "P_equ",
      "excluded_underperforming_baseline": true,
      "hp_combo_id": "C5",
      "recombine_strategy": "none",
      "retention": 0.5661375661375662,
      "run_id": "0d2b7ecddcc939b4e495cdb9eb8f789e",
      "seed": 22,
      "wall_time_s": 24.293945789337158
    },
    {
      "acc_task1_final": 0.106,
      "acc_task1_initial": 0.255,
      "arm": "P_equ",
      "excluded_underperforming_baseline": false,
      "hp_combo_id": "C5",
      "recombine_strategy": "none",
      "retention": 0.4156862745098039,
      "run_id": "ccf298c8b852b88751f9b893c71cabe5",
      "seed": 23,
      "wall_time_s": 21.753761053085327
    },
    {
      "acc_task1_final": 0.102,
      "acc_task1_initial": 0.22,
      "arm": "P_equ",
      "excluded_underperforming_baseline": false,
      "hp_combo_id": "C5",
      "recombine_strategy": "none",
      "retention": 0.4636363636363636,
      "run_id": "bcbc74245e12a6d1100576c2008bddff",
      "seed": 24,
      "wall_time_s": 19.44664716720581
    },
    {
      "acc_task1_final": 0.092,
      "acc_task1_initial": 0.243,
      "arm": "P_equ",
      "excluded_underperforming_baseline": false,
      "hp_combo_id": "C5",
      "recombine_strategy": "none",
      "retention": 0.3786008230452675,
      "run_id": "abb8f57e76ecc426d3b3752b67c798fb",
      "seed": 25,
      "wall_time_s": 13.870147705078125
    },
    {
      "acc_task1_final": 0.049,
      "acc_task1_initial": 0.298,
      "arm": "P_equ",
      "excluded_underperforming_baseline": false,
      "hp_combo_id": "C5",
      "recombine_strategy": "none",
      "retention": 0.1644295302013423,
      "run_id": "79b1dc032df21e9d91da7901d6d98d0a",
      "seed": 26,
      "wall_time_s": 10.933202981948853
    },
    {
      "acc_task1_final": 0.079,
      "acc_task1_initial": 0.146,
      "arm": "P_equ",
      "excluded_underperforming_baseline": true,
      "hp_combo_id": "C5",
      "recombine_strategy": "none",
      "retention": 0.541095890410959,
      "run_id": "3eadabbdc7d82188700564a98fe6b057",
      "seed": 27,
      "wall_time_s": 11.099148035049438
    },
    {
      "acc_task1_final": 0.094,
      "acc_task1_initial": 0.171,
      "arm": "P_equ",
      "excluded_underperforming_baseline": true,
      "hp_combo_id": "C5",
      "recombine_strategy": "none",
      "retention": 0.5497076023391813,
      "run_id": "e7fa3b1ad59091093439b5ef86f30fef",
      "seed": 28,
      "wall_time_s": 12.72506308555603
    },
    {
      "acc_task1_final": 0.11,
      "acc_task1_initial": 0.267,
      "arm": "P_equ",
      "excluded_underperforming_baseline": false,
      "hp_combo_id": "C5",
      "recombine_strategy": "none",
      "retention": 0.4119850187265917,
      "run_id": "d6f750db53cfa9783cf151bc200b7e8b",
      "seed": 29,
      "wall_time_s": 10.551885843276978
    },
    {
      "acc_task1_final": 0.097,
      "acc_task1_initial": 0.188,
      "arm": "P_max",
      "excluded_underperforming_baseline": true,
      "hp_combo_id": "C5",
      "recombine_strategy": "none",
      "retention": 0.5159574468085106,
      "run_id": "883ce9430b026c5e6899bbca3b9cd3e8",
      "seed": 0,
      "wall_time_s": 12.159713745117188
    },
    {
      "acc_task1_final": 0.076,
      "acc_task1_initial": 0.209,
      "arm": "P_max",
      "excluded_underperforming_baseline": false,
      "hp_combo_id": "C5",
      "recombine_strategy": "none",
      "retention": 0.36363636363636365,
      "run_id": "a598275d7d9d485caff20cfb95d43db8",
      "seed": 1,
      "wall_time_s": 10.768559217453003
    },
    {
      "acc_task1_final": 0.096,
      "acc_task1_initial": 0.209,
      "arm": "P_max",
      "excluded_underperforming_baseline": false,
      "hp_combo_id": "C5",
      "recombine_strategy": "none",
      "retention": 0.45933014354066987,
      "run_id": "235e45fb086889323182a423890121df",
      "seed": 2,
      "wall_time_s": 10.781436920166016
    },
    {
      "acc_task1_final": 0.08,
      "acc_task1_initial": 0.27,
      "arm": "P_max",
      "excluded_underperforming_baseline": false,
      "hp_combo_id": "C5",
      "recombine_strategy": "none",
      "retention": 0.2962962962962963,
      "run_id": "ce7763006f6ba6292cd9c27e5faca65c",
      "seed": 3,
      "wall_time_s": 13.174380779266357
    },
    {
      "acc_task1_final": 0.104,
      "acc_task1_initial": 0.268,
      "arm": "P_max",
      "excluded_underperforming_baseline": false,
      "hp_combo_id": "C5",
      "recombine_strategy": "none",
      "retention": 0.38805970149253727,
      "run_id": "61fd50ac6921b420a5e388bc311a75c5",
      "seed": 4,
      "wall_time_s": 10.881897926330566
    },
    {
      "acc_task1_final": 0.078,
      "acc_task1_initial": 0.238,
      "arm": "P_max",
      "excluded_underperforming_baseline": false,
      "hp_combo_id": "C5",
      "recombine_strategy": "none",
      "retention": 0.3277310924369748,
      "run_id": "e7acee150180e77260cd5ef694f4d915",
      "seed": 5,
      "wall_time_s": 12.345823049545288
    },
    {
      "acc_task1_final": 0.091,
      "acc_task1_initial": 0.247,
      "arm": "P_max",
      "excluded_underperforming_baseline": false,
      "hp_combo_id": "C5",
      "recombine_strategy": "none",
      "retention": 0.3684210526315789,
      "run_id": "d33acc73e2148aee8fe3b7d24d12d597",
      "seed": 6,
      "wall_time_s": 10.975959777832031
    },
    {
      "acc_task1_final": 0.066,
      "acc_task1_initial": 0.226,
      "arm": "P_max",
      "excluded_underperforming_baseline": false,
      "hp_combo_id": "C5",
      "recombine_strategy": "none",
      "retention": 0.2920353982300885,
      "run_id": "6918131b831406408cdcd4da25cb4f79",
      "seed": 7,
      "wall_time_s": 12.662802934646606
    },
    {
      "acc_task1_final": 0.109,
      "acc_task1_initial": 0.256,
      "arm": "P_max",
      "excluded_underperforming_baseline": false,
      "hp_combo_id": "C5",
      "recombine_strategy": "none",
      "retention": 0.42578125,
      "run_id": "47623f1aee6c47c0e35ce971cdacf3cd",
      "seed": 8,
      "wall_time_s": 11.9883291721344
    },
    {
      "acc_task1_final": 0.08,
      "acc_task1_initial": 0.274,
      "arm": "P_max",
      "excluded_underperforming_baseline": false,
      "hp_combo_id": "C5",
      "recombine_strategy": "none",
      "retention": 0.291970802919708,
      "run_id": "b9457cb9afa0a257bd637daaabbfe350",
      "seed": 9,
      "wall_time_s": 10.866336822509766
    },
    {
      "acc_task1_final": 0.086,
      "acc_task1_initial": 0.239,
      "arm": "P_max",
      "excluded_underperforming_baseline": false,
      "hp_combo_id": "C5",
      "recombine_strategy": "none",
      "retention": 0.3598326359832636,
      "run_id": "2ff2fbc2f945d07383b6485fcf00755f",
      "seed": 10,
      "wall_time_s": 10.774936199188232
    },
    {
      "acc_task1_final": 0.082,
      "acc_task1_initial": 0.244,
      "arm": "P_max",
      "excluded_underperforming_baseline": false,
      "hp_combo_id": "C5",
      "recombine_strategy": "none",
      "retention": 0.33606557377049184,
      "run_id": "8522a1762b96940f7d2bf052cf0c9542",
      "seed": 11,
      "wall_time_s": 11.380041360855103
    },
    {
      "acc_task1_final": 0.081,
      "acc_task1_initial": 0.206,
      "arm": "P_max",
      "excluded_underperforming_baseline": false,
      "hp_combo_id": "C5",
      "recombine_strategy": "none",
      "retention": 0.3932038834951457,
      "run_id": "8f00b24d1aa57d8734574f39a90142bb",
      "seed": 12,
      "wall_time_s": 11.868555784225464
    },
    {
      "acc_task1_final": 0.097,
      "acc_task1_initial": 0.212,
      "arm": "P_max",
      "excluded_underperforming_baseline": false,
      "hp_combo_id": "C5",
      "recombine_strategy": "none",
      "retention": 0.45754716981132076,
      "run_id": "ea06d91458918232086350ae18fd7779",
      "seed": 13,
      "wall_time_s": 24.9687979221344
    },
    {
      "acc_task1_final": 0.076,
      "acc_task1_initial": 0.24,
      "arm": "P_max",
      "excluded_underperforming_baseline": false,
      "hp_combo_id": "C5",
      "recombine_strategy": "none",
      "retention": 0.31666666666666665,
      "run_id": "2f26e7cad8a3875b82223a3785c6e1fc",
      "seed": 14,
      "wall_time_s": 28.31778383255005
    },
    {
      "acc_task1_final": 0.062,
      "acc_task1_initial": 0.253,
      "arm": "P_max",
      "excluded_underperforming_baseline": false,
      "hp_combo_id": "C5",
      "recombine_strategy": "none",
      "retention": 0.2450592885375494,
      "run_id": "3f151c51fe1015a42a2c97c23f598353",
      "seed": 15,
      "wall_time_s": 20.877338647842407
    },
    {
      "acc_task1_final": 0.103,
      "acc_task1_initial": 0.159,
      "arm": "P_max",
      "excluded_underperforming_baseline": true,
      "hp_combo_id": "C5",
      "recombine_strategy": "none",
      "retention": 0.6477987421383647,
      "run_id": "11a46ed111ff2e0cfd5d8f8a7ba3dada",
      "seed": 16,
      "wall_time_s": 18.648592233657837
    },
    {
      "acc_task1_final": 0.101,
      "acc_task1_initial": 0.197,
      "arm": "P_max",
      "excluded_underperforming_baseline": true,
      "hp_combo_id": "C5",
      "recombine_strategy": "none",
      "retention": 0.5126903553299492,
      "run_id": "597e8f75115bbf42e28ed2eb6f1a0118",
      "seed": 17,
      "wall_time_s": 15.766749382019043
    },
    {
      "acc_task1_final": 0.078,
      "acc_task1_initial": 0.24,
      "arm": "P_max",
      "excluded_underperforming_baseline": false,
      "hp_combo_id": "C5",
      "recombine_strategy": "none",
      "retention": 0.325,
      "run_id": "a21c7edf3fbd8e2ee1705a82c41e3c33",
      "seed": 18,
      "wall_time_s": 10.831068992614746
    },
    {
      "acc_task1_final": 0.085,
      "acc_task1_initial": 0.182,
      "arm": "P_max",
      "excluded_underperforming_baseline": true,
      "hp_combo_id": "C5",
      "recombine_strategy": "none",
      "retention": 0.4670329670329671,
      "run_id": "acf08827755056626d624b09feb97135",
      "seed": 19,
      "wall_time_s": 13.197412014007568
    },
    {
      "acc_task1_final": 0.083,
      "acc_task1_initial": 0.206,
      "arm": "P_max",
      "excluded_underperforming_baseline": false,
      "hp_combo_id": "C5",
      "recombine_strategy": "none",
      "retention": 0.40291262135922334,
      "run_id": "863fc02babfd76daea9af42cbdcf74b2",
      "seed": 20,
      "wall_time_s": 10.843183279037476
    },
    {
      "acc_task1_final": 0.082,
      "acc_task1_initial": 0.234,
      "arm": "P_max",
      "excluded_underperforming_baseline": false,
      "hp_combo_id": "C5",
      "recombine_strategy": "none",
      "retention": 0.3504273504273504,
      "run_id": "2af935f8bf1881c5c0f9a6cab433e9af",
      "seed": 21,
      "wall_time_s": 13.092830896377563
    },
    {
      "acc_task1_final": 0.107,
      "acc_task1_initial": 0.189,
      "arm": "P_max",
      "excluded_underperforming_baseline": true,
      "hp_combo_id": "C5",
      "recombine_strategy": "none",
      "retention": 0.5661375661375662,
      "run_id": "3d232f00ceec64d4e86473567192e4a4",
      "seed": 22,
      "wall_time_s": 12.32500696182251
    },
    {
      "acc_task1_final": 0.106,
      "acc_task1_initial": 0.255,
      "arm": "P_max",
      "excluded_underperforming_baseline": false,
      "hp_combo_id": "C5",
      "recombine_strategy": "none",
      "retention": 0.4156862745098039,
      "run_id": "09f697426ae8e5f676166ba8ad599e10",
      "seed": 23,
      "wall_time_s": 10.828291177749634
    },
    {
      "acc_task1_final": 0.102,
      "acc_task1_initial": 0.22,
      "arm": "P_max",
      "excluded_underperforming_baseline": false,
      "hp_combo_id": "C5",
      "recombine_strategy": "none",
      "retention": 0.4636363636363636,
      "run_id": "99e2baefd77abab7367b8409213bff66",
      "seed": 24,
      "wall_time_s": 16.100801706314087
    },
    {
      "acc_task1_final": 0.092,
      "acc_task1_initial": 0.243,
      "arm": "P_max",
      "excluded_underperforming_baseline": false,
      "hp_combo_id": "C5",
      "recombine_strategy": "none",
      "retention": 0.3786008230452675,
      "run_id": "f1979d9278b73e5febb0a8d040c98758",
      "seed": 25,
      "wall_time_s": 28.132248163223267
    },
    {
      "acc_task1_final": 0.049,
      "acc_task1_initial": 0.298,
      "arm": "P_max",
      "excluded_underperforming_baseline": false,
      "hp_combo_id": "C5",
      "recombine_strategy": "none",
      "retention": 0.1644295302013423,
      "run_id": "83d3c52215f159c9f5576e07a4020549",
      "seed": 26,
      "wall_time_s": 24.069519996643066
    },
    {
      "acc_task1_final": 0.079,
      "acc_task1_initial": 0.146,
      "arm": "P_max",
      "excluded_underperforming_baseline": true,
      "hp_combo_id": "C5",
      "recombine_strategy": "none",
      "retention": 0.541095890410959,
      "run_id": "c10d5908ac12acea47059acab895aa11",
      "seed": 27,
      "wall_time_s": 15.439027786254883
    },
    {
      "acc_task1_final": 0.094,
      "acc_task1_initial": 0.171,
      "arm": "P_max",
      "excluded_underperforming_baseline": true,
      "hp_combo_id": "C5",
      "recombine_strategy": "none",
      "retention": 0.5497076023391813,
      "run_id": "f8e437f7f05f9d29826fdca8ebcc7c14",
      "seed": 28,
      "wall_time_s": 15.293286800384521
    },
    {
      "acc_task1_final": 0.11,
      "acc_task1_initial": 0.267,
      "arm": "P_max",
      "excluded_underperforming_baseline": false,
      "hp_combo_id": "C5",
      "recombine_strategy": "none",
      "retention": 0.4119850187265917,
      "run_id": "2259f2aa7119269fb4056e6bf1bfd491",
      "seed": 29,
      "wall_time_s": 13.53920602798462
    }
  ],
  "commit_sha": "14c9d326ec7ed31044bf1904fd180fd3367a9df9",
  "data_dir": "/Users/electron/hypneum-lab/dream-of-kiki/experiments/g4_sexto_test/data",
  "date": "2026-05-03",
  "n_seeds": 30,
  "smoke": false,
  "strategies": [
    "mog",
    "none"
  ],
  "verdict": {
    "h6a_recombine_strategy": {
      "alpha_per_test": 0.016666666666666666,
      "fail_to_reject_h0": true,
      "h6a_recombine_empty_confirmed": true,
      "hedges_g_mog_vs_none": 0.056983484124934085,
      "mean_p_max_mog": 0.36219385007335886,
      "mean_p_max_none": 0.35801370875454774,
      "n_p_max_mog": 23,
      "n_p_max_none": 23,
      "welch_p_two_sided": 0.8450374128979047,
      "welch_t": 0.196610868493051
    }
  },
  "wall_time_s": 4834.732341766357
}